{"html_attributions": [], "results": [{"business_status": "OPERATIONAL", "geometry": {"location": {"lat": 32.864183, "lng": 35.712484}, "viewport": {"northeast": {"lat": 32.86523492989271, "lng": 35.71391847989272}, "southwest": {"lat": 32.86253527010727, "lng": 35.71121882010728}}}, "icon": "https://maps.gstatic.com/mapfiles/place_api/icons/v1/png_71/worship_jewish-71.png", "icon_background_color": "#7B9EB0", "icon_mask_base_uri": "https://maps.gstatic.com/mapfiles/place_api/icons/v2/worship_jewish_pinlet", "name": "Dir Aziz Synagogue", "opening_hours": {"open_now": true}, "photos": [{"height": 3024, "html_attributions": ["<a href=\"https://maps.google.com/maps/contrib/102545306367902434987\">mashkin1993@gmail.com</a>"], "photo_reference": "AeJbb3fkJr9DYKtSQHCXG9BWBO0ppSdCuHxO29T2iJ2PfDMGvgfRZDi83C97dKQPFwLrgdp-phKNiYsci6u22prBgnfczTKYdoeUVwzZKtgzbw9KlSEzgicWqtH70CHm7Pt97H1OlBYbK6I0lRKN3smcCp7ChOia3THskyNm5q7Pwqv7s98", "width": 4032}], "place_id": "ChIJW-DFkewaHBUR8NKerVlKz9A", "plus_code": {"compound_code": "VP76+MX \u05e7\u05e6\u05e8\u05d9\u05df", "global_code": "8G4QVP76+MX"}, "rating": 4.3, "reference": "ChIJW-DFkewaHBUR8NKerVlKz9A", "scope": "GOOGLE", "types": ["synagogue", "place_of_worship", "point_of_interest", "establishment"], "user_ratings_total": 310, "vicinity": "32\u00b051'51.1\"N 35\u00b042'44., 9, Qatsrin"}, {"business_status": "OPERATIONAL", "geometry": {"location": {"lat": 32.902418, "lng": 35.740639}, "viewport": {"northeast": {"lat": 32.90376782989271, "lng": 35.74198882989273}, "southwest": {"lat": 32.90106817010727, "lng": 35.73928917010728}}}, "icon": "https://maps.gstatic.com/mapfiles/place_api/icons/v1/png_71/worship_jewish-71.png", "icon_background_color": "#7B9EB0", "icon_mask_base_uri": "https://maps.gstatic.com/mapfiles/place_api/icons/v2/worship_jewish_pinlet", "name": "\u0414\u0440\u0435\u0432\u043d\u044f\u044f \u0421\u0438\u043d\u0430\u0433\u043e\u0433\u0430 (Ancient Synagogue)", "opening_hours": {"open_now": true}, "photos": [{"height": 4032, "html_attributions": ["<a href=\"https://maps.google.com/maps/contrib/106189495642269583825\">Michal Moore</a>"], "photo_reference": "AeJbb3cgnpivs2HhQ9OeoT7qiqkqk4m-WWlYe_fNFlIJ54Wy2HAYh8F-rCFvyKQz7nE13G29Foo0d4PzzN4eBq5qLqBqtfWEMjYYlFjqSNz08x5i7YbeKIkKdPKlyooWZHxwHpxVxdgjuvK6yGfIlpClogqmAHh9vMbVvk55V6Y0qYg4H5xq", "width": 3024}], "place_id": "ChIJY_Fc5K0bHBURJdGPe88IaBs", "rating": 5, "reference": "ChIJY_Fc5K0bHBURJdGPe88IaBs", "scope": "GOOGLE", "types": ["synagogue", "place_of_worship", "point_of_interest", "establishment"], "user_ratings_total": 1, "vicinity": "Unnamed Road, Gamla"}], "status": "OK"}
